gencon_miner/GenconMiner.py
gencon_miner/__init__.py
gencon_miner/exceptions.py
genconminer-0.1.7.dist-info/entry_points.txt
genconminer-0.1.7.dist-info/LICENSE
genconminer-0.1.7.dist-info/WHEEL
genconminer-0.1.7.dist-info/METADATA
genconminer-0.1.7.dist-info/RECORD
