Metadata-Version: 2.1
Name: genconminer
Version: 0.1.7
Summary: Wraps Pip packages (beautifulsoup and requests) to a more concise content extractor
Home-page: https://github.com/mamerisawesome/GenconMiner
License: MIT
Author: Almer Mendoza
Author-email: amendoza@stratpoint.com
Requires-Python: >=2.7, !=3.0.*, !=3.1.*, !=3.2.*, !=3.3.*, !=3.4.*, !=3.5.*
Classifier: License :: OSI Approved :: MIT License
Classifier: Programming Language :: Python :: 2
Classifier: Programming Language :: Python :: 2.7
Classifier: Programming Language :: Python :: 3
Classifier: Programming Language :: Python :: 3.6
Classifier: Programming Language :: Python :: 3.7
Requires-Dist: beautifulsoup4 (>=4.7,<5.0)
Requires-Dist: requests (>=2,<3)
Project-URL: Repository, https://github.com/mamerisawesome/GenconMiner
